[
  {
    "id": "eb7dfd25-5414-4f6e-8279-856f819abc4a",
    "memory_type": "short_term",
    "content": "{\"job_id\": \"2cc5238b-fe07-4803-93ac-73591640a59e\", \"video_id\": \"dQw4w9WgXcQ\", \"status\": \"queued\", \"phase\": null, \"progress\": 0.0, \"cached\": false, \"created_at\": \"2025-09-05T10:20:51.886415+00:00\", \"updated_at\": \"2025-09-05T10:20:51.886415+00:00\", \"subtitle_availability\": {\"available\": true, \"manual_subtitles\": [\"en\", \"de-DE\", \"ja\", \"pt-BR\", \"es-419\"], \"auto_captions\": [\"ar\", \"zh-Hant\", \"nl\", \"en-orig\", \"en\", \"fr\", \"de\", \"hi\", \"id\", \"it\", \"ja\", \"ko\", \"pt\", \"ru\", \"es\", \"th\", \"tr\", \"uk\", \"vi\", \"ab\", \"aa\", \"af\", \"ak\", \"sq\", \"am\", \"hy\", \"as\", \"ay\", \"az\", \"bn\", \"ba\", \"eu\", \"be\", \"bho\", \"bs\", \"br\", \"bg\", \"my\", \"ca\", \"ceb\", \"zh-Hans\", \"co\", \"hr\", \"cs\", \"da\", \"dv\", \"dz\", \"eo\", \"et\", \"ee\", \"fo\", \"fj\", \"fil\", \"fi\", \"gaa\", \"gl\", \"lg\", \"ka\", \"el\", \"gn\", \"gu\", \"ht\", \"ha\", \"haw\", \"iw\", \"hmn\", \"hu\", \"is\", \"ig\", \"iu\", \"ga\", \"jv\", \"kl\", \"kn\", \"kk\", \"kha\", \"km\", \"rw\", \"kri\", \"ku\", \"ky\", \"lo\", \"la\", \"lv\", \"ln\", \"lt\", \"lua\", \"luo\", \"lb\", \"mk\", \"mg\", \"ms\", \"ml\", \"mt\", \"gv\", \"mi\", \"mr\", \"mn\", \"mfe\", \"ne\", \"new\", \"nso\", \"no\", \"ny\", \"oc\", \"or\", \"om\", \"os\", \"pam\", \"ps\", \"fa\", \"pl\", \"pt-PT\", \"pa\", \"qu\", \"ro\", \"rn\", \"sm\", \"sg\", \"sa\", \"gd\", \"sr\", \"crs\", \"sn\", \"sd\", \"si\", \"sk\", \"sl\", \"so\", \"st\", \"su\", \"sw\", \"ss\", \"sv\", \"tg\", \"ta\", \"tt\", \"te\", \"bo\", \"ti\", \"to\", \"ts\", \"tn\", \"tum\", \"tk\", \"ur\", \"ug\", \"uz\", \"ve\", \"war\", \"cy\", \"fy\", \"wo\", \"xh\", \"yi\", \"yo\", \"zu\"], \"selected_lang\": \"en\", \"confidence_score\": 0.95}}",
    "metadata": {
      "type": "cache",
      "key": "trailtag:3cea54087de3dd9d95f028308d7fb964",
      "original_query": "job:2cc5238b-fe07-4803-93ac-73591640a59e",
      "ttl": null,
      "stored_at": 1757067651.8865201
    },
    "agent_role": null,
    "task_id": null,
    "video_id": null,
    "created_at": "2025-09-05T10:20:51.886530+00:00",
    "updated_at": "2025-09-05T10:20:51.886531+00:00",
    "expires_at": null
  },
  {
    "id": "1e2a1154-5bb0-41c2-89ce-3d9f7d415fe5",
    "memory_type": "short_term",
    "content": "2cc5238b-fe07-4803-93ac-73591640a59e",
    "metadata": {
      "type": "cache",
      "key": "trailtag:d0a1ed88718b5b2b62d16ba9b7b81182",
      "original_query": "video_job:dQw4w9WgXcQ",
      "ttl": null,
      "stored_at": 1757067651.887111
    },
    "agent_role": null,
    "task_id": null,
    "video_id": null,
    "created_at": "2025-09-05T10:20:51.887122+00:00",
    "updated_at": "2025-09-05T10:20:51.887124+00:00",
    "expires_at": null
  },
  {
    "id": "30cd907a-c4d9-4eb1-b456-c79059a9035b",
    "memory_type": "short_term",
    "content": "{\"job_id\": \"2cc5238b-fe07-4803-93ac-73591640a59e\", \"video_id\": \"dQw4w9WgXcQ\", \"status\": \"running\", \"phase\": \"metadata\", \"progress\": 0.0, \"cached\": false, \"created_at\": \"2025-09-05T10:20:51.893734+00:00\", \"updated_at\": \"2025-09-05T10:20:51.893734+00:00\"}",
    "metadata": {
      "type": "cache",
      "key": "trailtag:3cea54087de3dd9d95f028308d7fb964",
      "original_query": "job:2cc5238b-fe07-4803-93ac-73591640a59e",
      "ttl": null,
      "stored_at": 1757067651.893773
    },
    "agent_role": null,
    "task_id": null,
    "video_id": null,
    "created_at": "2025-09-05T10:20:51.893788+00:00",
    "updated_at": "2025-09-05T10:20:51.893789+00:00",
    "expires_at": null
  },
  {
    "id": "8ff27e60-8c3b-4114-974c-8db4b5b6baf2",
    "memory_type": "short_term",
    "content": "{\"job_id\": \"2cc5238b-fe07-4803-93ac-73591640a59e\", \"video_id\": \"dQw4w9WgXcQ\", \"status\": \"running\", \"phase\": \"metadata\", \"progress\": 5, \"cached\": false, \"created_at\": \"2025-09-05T10:20:51.894040+00:00\", \"updated_at\": \"2025-09-05T10:20:51.894040+00:00\"}",
    "metadata": {
      "type": "cache",
      "key": "trailtag:3cea54087de3dd9d95f028308d7fb964",
      "original_query": "job:2cc5238b-fe07-4803-93ac-73591640a59e",
      "ttl": null,
      "stored_at": 1757067651.894059
    },
    "agent_role": null,
    "task_id": null,
    "video_id": null,
    "created_at": "2025-09-05T10:20:51.894066+00:00",
    "updated_at": "2025-09-05T10:20:51.894067+00:00",
    "expires_at": null
  },
  {
    "id": "0605499a-cab8-48f9-8280-6a95e74f9b0a",
    "memory_type": "short_term",
    "content": "{\"job_id\": \"2cc5238b-fe07-4803-93ac-73591640a59e\", \"video_id\": \"dQw4w9WgXcQ\", \"status\": \"failed\", \"phase\": \"geocode\", \"progress\": 0, \"cached\": false, \"created_at\": \"2025-09-05T10:20:52.116894+00:00\", \"updated_at\": \"2025-09-05T10:20:52.116894+00:00\", \"error\": {\"type\": \"exception\", \"message\": \"'video_metadata_extraction_task'\"}}",
    "metadata": {
      "type": "cache",
      "key": "trailtag:3cea54087de3dd9d95f028308d7fb964",
      "original_query": "job:2cc5238b-fe07-4803-93ac-73591640a59e",
      "ttl": null,
      "stored_at": 1757067652.116935
    },
    "agent_role": null,
    "task_id": null,
    "video_id": null,
    "created_at": "2025-09-05T10:20:52.116955+00:00",
    "updated_at": "2025-09-05T10:20:52.116955+00:00",
    "expires_at": null
  },
  {
    "id": "67bc54f3-2780-4b7a-b012-18f10a2cd0ba",
    "memory_type": "short_term",
    "content": "DELETED",
    "metadata": {
      "type": "cache",
      "key": "trailtag:d0a1ed88718b5b2b62d16ba9b7b81182",
      "deleted": true,
      "deleted_at": 1757067652.117324
    },
    "agent_role": null,
    "task_id": null,
    "video_id": null,
    "created_at": "2025-09-05T10:20:52.117332+00:00",
    "updated_at": "2025-09-05T10:20:52.117333+00:00",
    "expires_at": null
  },
  {
    "id": "1f356346-6aa2-4f73-83ec-5c770e0084c8",
    "memory_type": "short_term",
    "content": "{\"job_id\": \"aac1632b-8e21-4041-a5de-5b3e5b78433b\", \"video_id\": \"kp2Prt6jbkc\", \"status\": \"queued\", \"phase\": null, \"progress\": 0.0, \"cached\": false, \"created_at\": \"2025-09-05T14:17:32.611350+00:00\", \"updated_at\": \"2025-09-05T14:17:32.611350+00:00\", \"subtitle_availability\": {\"available\": true, \"manual_subtitles\": [], \"auto_captions\": [\"ar\", \"zh-Hant\", \"nl\", \"fr\", \"de\", \"hi\", \"id\", \"it\", \"ja\", \"ko\", \"pt\", \"ru\", \"es\", \"th\", \"uk\", \"vi\"], \"selected_lang\": null, \"confidence_score\": 0.75}}",
    "metadata": {
      "type": "cache",
      "key": "trailtag:ab615f1ad80e066d393bab43a9de8116",
      "original_query": "job:aac1632b-8e21-4041-a5de-5b3e5b78433b",
      "ttl": null,
      "stored_at": 1757081852.611528
    },
    "agent_role": null,
    "task_id": null,
    "video_id": null,
    "created_at": "2025-09-05T14:17:32.611558+00:00",
    "updated_at": "2025-09-05T14:17:32.611560+00:00",
    "expires_at": null
  },
  {
    "id": "b9ed483b-5eae-42e1-b486-612b96878d1e",
    "memory_type": "short_term",
    "content": "aac1632b-8e21-4041-a5de-5b3e5b78433b",
    "metadata": {
      "type": "cache",
      "key": "trailtag:003df7448e5e1d3435634e2bae6d1ca7",
      "original_query": "video_job:kp2Prt6jbkc",
      "ttl": null,
      "stored_at": 1757081852.613568
    },
    "agent_role": null,
    "task_id": null,
    "video_id": null,
    "created_at": "2025-09-05T14:17:32.613603+00:00",
    "updated_at": "2025-09-05T14:17:32.613608+00:00",
    "expires_at": null
  },
  {
    "id": "5cb40544-fc26-4a7b-a2aa-a9819f3c780e",
    "memory_type": "short_term",
    "content": "{\"job_id\": \"aac1632b-8e21-4041-a5de-5b3e5b78433b\", \"video_id\": \"kp2Prt6jbkc\", \"status\": \"running\", \"phase\": \"metadata\", \"progress\": 0.0, \"cached\": false, \"created_at\": \"2025-09-05T14:17:32.631262+00:00\", \"updated_at\": \"2025-09-05T14:17:32.631262+00:00\"}",
    "metadata": {
      "type": "cache",
      "key": "trailtag:ab615f1ad80e066d393bab43a9de8116",
      "original_query": "job:aac1632b-8e21-4041-a5de-5b3e5b78433b",
      "ttl": null,
      "stored_at": 1757081852.631331
    },
    "agent_role": null,
    "task_id": null,
    "video_id": null,
    "created_at": "2025-09-05T14:17:32.631362+00:00",
    "updated_at": "2025-09-05T14:17:32.631363+00:00",
    "expires_at": null
  },
  {
    "id": "ab5d1cb9-0360-459d-b843-b48b962002e9",
    "memory_type": "short_term",
    "content": "{\"job_id\": \"aac1632b-8e21-4041-a5de-5b3e5b78433b\", \"video_id\": \"kp2Prt6jbkc\", \"status\": \"running\", \"phase\": \"metadata\", \"progress\": 5, \"cached\": false, \"created_at\": \"2025-09-05T14:17:32.632222+00:00\", \"updated_at\": \"2025-09-05T14:17:32.632222+00:00\"}",
    "metadata": {
      "type": "cache",
      "key": "trailtag:ab615f1ad80e066d393bab43a9de8116",
      "original_query": "job:aac1632b-8e21-4041-a5de-5b3e5b78433b",
      "ttl": null,
      "stored_at": 1757081852.6322691
    },
    "agent_role": null,
    "task_id": null,
    "video_id": null,
    "created_at": "2025-09-05T14:17:32.632285+00:00",
    "updated_at": "2025-09-05T14:17:32.632286+00:00",
    "expires_at": null
  },
  {
    "id": "f237ece9-8e74-4f5d-a5b8-1f39fcc30088",
    "memory_type": "short_term",
    "content": "{\"job_id\": \"aac1632b-8e21-4041-a5de-5b3e5b78433b\", \"video_id\": \"kp2Prt6jbkc\", \"status\": \"failed\", \"phase\": \"geocode\", \"progress\": 0, \"cached\": false, \"created_at\": \"2025-09-05T14:17:32.860362+00:00\", \"updated_at\": \"2025-09-05T14:17:32.860362+00:00\", \"error\": {\"type\": \"exception\", \"message\": \"'video_metadata_extraction_task'\"}}",
    "metadata": {
      "type": "cache",
      "key": "trailtag:ab615f1ad80e066d393bab43a9de8116",
      "original_query": "job:aac1632b-8e21-4041-a5de-5b3e5b78433b",
      "ttl": null,
      "stored_at": 1757081852.860401
    },
    "agent_role": null,
    "task_id": null,
    "video_id": null,
    "created_at": "2025-09-05T14:17:32.860421+00:00",
    "updated_at": "2025-09-05T14:17:32.860421+00:00",
    "expires_at": null
  },
  {
    "id": "7c1ab450-ad7e-4d3b-a78d-f21cb2950570",
    "memory_type": "short_term",
    "content": "DELETED",
    "metadata": {
      "type": "cache",
      "key": "trailtag:003df7448e5e1d3435634e2bae6d1ca7",
      "deleted": true,
      "deleted_at": 1757081852.8608809
    },
    "agent_role": null,
    "task_id": null,
    "video_id": null,
    "created_at": "2025-09-05T14:17:32.860888+00:00",
    "updated_at": "2025-09-05T14:17:32.860889+00:00",
    "expires_at": null
  },
  {
    "id": "7ca5cd9e-86ad-465a-938b-61429592f27c",
    "memory_type": "short_term",
    "content": "{\"job_id\": \"12345\", \"status\": \"queued\", \"progress\": 0}",
    "metadata": {
      "type": "cache",
      "key": "trailtag:4a9f14ef2967794af4dfd643a0150608",
      "original_query": "test_job:12345",
      "ttl": null,
      "stored_at": 1757082307.03969
    },
    "agent_role": null,
    "task_id": null,
    "video_id": null,
    "created_at": "2025-09-05T14:25:07.039705+00:00",
    "updated_at": "2025-09-05T14:25:07.039706+00:00",
    "expires_at": null
  },
  {
    "id": "14bc1191-d677-4303-9d39-1cab3c77c63d",
    "memory_type": "short_term",
    "content": "{\"job_id\": \"12345\", \"status\": \"queued\", \"progress\": 0}",
    "metadata": {
      "type": "cache",
      "key": "trailtag:4a9f14ef2967794af4dfd643a0150608",
      "original_query": "test_job:12345",
      "ttl": null,
      "stored_at": 1757082442.73523
    },
    "agent_role": null,
    "task_id": null,
    "video_id": null,
    "created_at": "2025-09-05T14:27:22.735251+00:00",
    "updated_at": "2025-09-05T14:27:22.735253+00:00",
    "expires_at": null
  },
  {
    "id": "13e0774a-fd21-4474-99d6-07b2910575cf",
    "memory_type": "short_term",
    "content": "{\"job_id\": \"12345\", \"status\": \"queued\", \"progress\": 0}",
    "metadata": {
      "type": "cache",
      "key": "trailtag:4a9f14ef2967794af4dfd643a0150608",
      "original_query": "test_job:12345",
      "ttl": null,
      "stored_at": 1757082568.7230358
    },
    "agent_role": null,
    "task_id": null,
    "video_id": null,
    "created_at": "2025-09-05T14:29:28.723057+00:00",
    "updated_at": "2025-09-05T14:29:28.723059+00:00",
    "expires_at": null
  },
  {
    "id": "78e140f3-860d-4161-9cf1-c21334c1c7a6",
    "memory_type": "short_term",
    "content": "{\"job_id\": \"54fbe32e-1bbd-4ae9-9b27-74828055c505\", \"video_id\": \"kp2Prt6jbkc\", \"status\": \"queued\", \"phase\": null, \"progress\": 0.0, \"cached\": false, \"created_at\": \"2025-09-05T15:25:30.322745+00:00\", \"updated_at\": \"2025-09-05T15:25:30.322745+00:00\", \"subtitle_availability\": {\"available\": true, \"manual_subtitles\": [], \"auto_captions\": [\"ar\", \"zh-Hant\", \"nl\", \"fr\", \"de\", \"hi\", \"id\", \"it\", \"ja\", \"ko\", \"pt\", \"ru\", \"es\", \"th\", \"uk\", \"vi\"], \"selected_lang\": null, \"confidence_score\": 0.75}}",
    "metadata": {
      "type": "cache",
      "key": "trailtag:44fb9c9a31ac26f8bcb595e13a7764c1",
      "original_query": "job:54fbe32e-1bbd-4ae9-9b27-74828055c505",
      "ttl": null,
      "stored_at": 1757085930.322894
    },
    "agent_role": null,
    "task_id": null,
    "video_id": null,
    "created_at": "2025-09-05T15:25:30.322904+00:00",
    "updated_at": "2025-09-05T15:25:30.322905+00:00",
    "expires_at": null
  },
  {
    "id": "89bdbb13-c894-4197-bb9d-2cf322b5d49b",
    "memory_type": "short_term",
    "content": "54fbe32e-1bbd-4ae9-9b27-74828055c505",
    "metadata": {
      "type": "cache",
      "key": "trailtag:003df7448e5e1d3435634e2bae6d1ca7",
      "original_query": "video_job:kp2Prt6jbkc",
      "ttl": null,
      "stored_at": 1757085930.323792
    },
    "agent_role": null,
    "task_id": null,
    "video_id": null,
    "created_at": "2025-09-05T15:25:30.323807+00:00",
    "updated_at": "2025-09-05T15:25:30.323808+00:00",
    "expires_at": null
  },
  {
    "id": "845056d0-97f7-46fd-8613-2f9a8672022d",
    "memory_type": "short_term",
    "content": "{\"job_id\": \"54fbe32e-1bbd-4ae9-9b27-74828055c505\", \"video_id\": \"kp2Prt6jbkc\", \"status\": \"running\", \"phase\": \"metadata\", \"progress\": 0.0, \"cached\": false, \"created_at\": \"2025-09-05T15:25:30.322745+00:00\", \"updated_at\": \"2025-09-05T15:25:30.334824+00:00\", \"subtitle_availability\": {\"available\": true, \"manual_subtitles\": [], \"auto_captions\": [\"ar\", \"zh-Hant\", \"nl\", \"fr\", \"de\", \"hi\", \"id\", \"it\", \"ja\", \"ko\", \"pt\", \"ru\", \"es\", \"th\", \"uk\", \"vi\"], \"selected_lang\": null, \"confidence_score\": 0.75}}",
    "metadata": {
      "type": "cache",
      "key": "trailtag:44fb9c9a31ac26f8bcb595e13a7764c1",
      "original_query": "job:54fbe32e-1bbd-4ae9-9b27-74828055c505",
      "ttl": null,
      "stored_at": 1757085930.334879
    },
    "agent_role": null,
    "task_id": null,
    "video_id": null,
    "created_at": "2025-09-05T15:25:30.334898+00:00",
    "updated_at": "2025-09-05T15:25:30.334899+00:00",
    "expires_at": null
  },
  {
    "id": "a2e81ee0-5b16-4e74-b103-4aae741e53e5",
    "memory_type": "short_term",
    "content": "{\"job_id\": \"54fbe32e-1bbd-4ae9-9b27-74828055c505\", \"video_id\": \"kp2Prt6jbkc\", \"status\": \"running\", \"phase\": \"metadata\", \"progress\": 5, \"cached\": false, \"created_at\": \"2025-09-05T15:25:30.322745+00:00\", \"updated_at\": \"2025-09-05T15:25:30.335454+00:00\", \"subtitle_availability\": {\"available\": true, \"manual_subtitles\": [], \"auto_captions\": [\"ar\", \"zh-Hant\", \"nl\", \"fr\", \"de\", \"hi\", \"id\", \"it\", \"ja\", \"ko\", \"pt\", \"ru\", \"es\", \"th\", \"uk\", \"vi\"], \"selected_lang\": null, \"confidence_score\": 0.75}}",
    "metadata": {
      "type": "cache",
      "key": "trailtag:44fb9c9a31ac26f8bcb595e13a7764c1",
      "original_query": "job:54fbe32e-1bbd-4ae9-9b27-74828055c505",
      "ttl": null,
      "stored_at": 1757085930.3354838
    },
    "agent_role": null,
    "task_id": null,
    "video_id": null,
    "created_at": "2025-09-05T15:25:30.335492+00:00",
    "updated_at": "2025-09-05T15:25:30.335492+00:00",
    "expires_at": null
  },
  {
    "id": "c6ce45ac-ff98-4d89-bbed-c81ad10cc21f",
    "memory_type": "short_term",
    "content": "{\"job_id\": \"54fbe32e-1bbd-4ae9-9b27-74828055c505\", \"video_id\": \"kp2Prt6jbkc\", \"status\": \"failed\", \"phase\": \"geocode\", \"progress\": 0, \"cached\": false, \"created_at\": \"2025-09-05T15:25:30.322745+00:00\", \"updated_at\": \"2025-09-05T15:25:30.532156+00:00\", \"subtitle_availability\": {\"available\": true, \"manual_subtitles\": [], \"auto_captions\": [\"ar\", \"zh-Hant\", \"nl\", \"fr\", \"de\", \"hi\", \"id\", \"it\", \"ja\", \"ko\", \"pt\", \"ru\", \"es\", \"th\", \"uk\", \"vi\"], \"selected_lang\": null, \"confidence_score\": 0.75}, \"error\": {\"type\": \"exception\", \"message\": \"'video_metadata_extraction_task'\"}}",
    "metadata": {
      "type": "cache",
      "key": "trailtag:44fb9c9a31ac26f8bcb595e13a7764c1",
      "original_query": "job:54fbe32e-1bbd-4ae9-9b27-74828055c505",
      "ttl": null,
      "stored_at": 1757085930.532214
    },
    "agent_role": null,
    "task_id": null,
    "video_id": null,
    "created_at": "2025-09-05T15:25:30.532238+00:00",
    "updated_at": "2025-09-05T15:25:30.532238+00:00",
    "expires_at": null
  },
  {
    "id": "bb6724e4-a654-4262-8eea-480c3acf2233",
    "memory_type": "short_term",
    "content": "DELETED",
    "metadata": {
      "type": "cache",
      "key": "trailtag:003df7448e5e1d3435634e2bae6d1ca7",
      "deleted": true,
      "deleted_at": 1757085930.533387
    },
    "agent_role": null,
    "task_id": null,
    "video_id": null,
    "created_at": "2025-09-05T15:25:30.533399+00:00",
    "updated_at": "2025-09-05T15:25:30.533401+00:00",
    "expires_at": null
  },
  {
    "id": "71821755-57d7-4d5e-ae75-b49ef954558d",
    "memory_type": "short_term",
    "content": "{\"job_id\": \"02c022d3-9c00-4de7-8f02-a77172c89d7a\", \"video_id\": \"kp2Prt6jbkc\", \"status\": \"queued\", \"phase\": null, \"progress\": 0.0, \"cached\": false, \"created_at\": \"2025-09-05T15:26:02.434657+00:00\", \"updated_at\": \"2025-09-05T15:26:02.434657+00:00\", \"subtitle_availability\": {\"available\": true, \"manual_subtitles\": [], \"auto_captions\": [\"ar\", \"zh-Hant\", \"nl\", \"fr\", \"de\", \"hi\", \"id\", \"it\", \"ja\", \"ko\", \"pt\", \"ru\", \"es\", \"th\", \"uk\", \"vi\"], \"selected_lang\": null, \"confidence_score\": 0.75}}",
    "metadata": {
      "type": "cache",
      "key": "trailtag:17aabb34406536a4c7a07a64cc7973bd",
      "original_query": "job:02c022d3-9c00-4de7-8f02-a77172c89d7a",
      "ttl": null,
      "stored_at": 1757085962.434745
    },
    "agent_role": null,
    "task_id": null,
    "video_id": null,
    "created_at": "2025-09-05T15:26:02.434763+00:00",
    "updated_at": "2025-09-05T15:26:02.434764+00:00",
    "expires_at": null
  },
  {
    "id": "a1a5a4e3-b17b-4995-8a37-928be0066db3",
    "memory_type": "short_term",
    "content": "02c022d3-9c00-4de7-8f02-a77172c89d7a",
    "metadata": {
      "type": "cache",
      "key": "trailtag:003df7448e5e1d3435634e2bae6d1ca7",
      "original_query": "video_job:kp2Prt6jbkc",
      "ttl": null,
      "stored_at": 1757085962.436291
    },
    "agent_role": null,
    "task_id": null,
    "video_id": null,
    "created_at": "2025-09-05T15:26:02.436310+00:00",
    "updated_at": "2025-09-05T15:26:02.436312+00:00",
    "expires_at": null
  },
  {
    "id": "d5d04b0d-5723-442b-a542-7ee727fcd503",
    "memory_type": "short_term",
    "content": "{\"job_id\": \"02c022d3-9c00-4de7-8f02-a77172c89d7a\", \"video_id\": \"kp2Prt6jbkc\", \"status\": \"running\", \"phase\": \"metadata\", \"progress\": 0.0, \"cached\": false, \"created_at\": \"2025-09-05T15:26:02.434657+00:00\", \"updated_at\": \"2025-09-05T15:26:02.440988+00:00\", \"subtitle_availability\": {\"available\": true, \"manual_subtitles\": [], \"auto_captions\": [\"ar\", \"zh-Hant\", \"nl\", \"fr\", \"de\", \"hi\", \"id\", \"it\", \"ja\", \"ko\", \"pt\", \"ru\", \"es\", \"th\", \"uk\", \"vi\"], \"selected_lang\": null, \"confidence_score\": 0.75}}",
    "metadata": {
      "type": "cache",
      "key": "trailtag:17aabb34406536a4c7a07a64cc7973bd",
      "original_query": "job:02c022d3-9c00-4de7-8f02-a77172c89d7a",
      "ttl": null,
      "stored_at": 1757085962.441083
    },
    "agent_role": null,
    "task_id": null,
    "video_id": null,
    "created_at": "2025-09-05T15:26:02.441109+00:00",
    "updated_at": "2025-09-05T15:26:02.441109+00:00",
    "expires_at": null
  },
  {
    "id": "1a1cd3af-8a05-4475-b50b-dfce90bde2a4",
    "memory_type": "short_term",
    "content": "{\"job_id\": \"02c022d3-9c00-4de7-8f02-a77172c89d7a\", \"video_id\": \"kp2Prt6jbkc\", \"status\": \"running\", \"phase\": \"metadata\", \"progress\": 5, \"cached\": false, \"created_at\": \"2025-09-05T15:26:02.434657+00:00\", \"updated_at\": \"2025-09-05T15:26:02.442259+00:00\", \"subtitle_availability\": {\"available\": true, \"manual_subtitles\": [], \"auto_captions\": [\"ar\", \"zh-Hant\", \"nl\", \"fr\", \"de\", \"hi\", \"id\", \"it\", \"ja\", \"ko\", \"pt\", \"ru\", \"es\", \"th\", \"uk\", \"vi\"], \"selected_lang\": null, \"confidence_score\": 0.75}}",
    "metadata": {
      "type": "cache",
      "key": "trailtag:17aabb34406536a4c7a07a64cc7973bd",
      "original_query": "job:02c022d3-9c00-4de7-8f02-a77172c89d7a",
      "ttl": null,
      "stored_at": 1757085962.442317
    },
    "agent_role": null,
    "task_id": null,
    "video_id": null,
    "created_at": "2025-09-05T15:26:02.442330+00:00",
    "updated_at": "2025-09-05T15:26:02.442331+00:00",
    "expires_at": null
  },
  {
    "id": "2e9e8319-102e-4870-a308-3797e41c0b68",
    "memory_type": "short_term",
    "content": "{\"job_id\": \"02c022d3-9c00-4de7-8f02-a77172c89d7a\", \"video_id\": \"kp2Prt6jbkc\", \"status\": \"failed\", \"phase\": \"geocode\", \"progress\": 0, \"cached\": false, \"created_at\": \"2025-09-05T15:26:02.434657+00:00\", \"updated_at\": \"2025-09-05T15:26:02.846356+00:00\", \"subtitle_availability\": {\"available\": true, \"manual_subtitles\": [], \"auto_captions\": [\"ar\", \"zh-Hant\", \"nl\", \"fr\", \"de\", \"hi\", \"id\", \"it\", \"ja\", \"ko\", \"pt\", \"ru\", \"es\", \"th\", \"uk\", \"vi\"], \"selected_lang\": null, \"confidence_score\": 0.75}, \"error\": {\"type\": \"exception\", \"message\": \"\\\"Crew\\\" object has no field \\\"kickoff\\\"\"}}",
    "metadata": {
      "type": "cache",
      "key": "trailtag:17aabb34406536a4c7a07a64cc7973bd",
      "original_query": "job:02c022d3-9c00-4de7-8f02-a77172c89d7a",
      "ttl": null,
      "stored_at": 1757085962.846407
    },
    "agent_role": null,
    "task_id": null,
    "video_id": null,
    "created_at": "2025-09-05T15:26:02.846420+00:00",
    "updated_at": "2025-09-05T15:26:02.846420+00:00",
    "expires_at": null
  },
  {
    "id": "51c0557d-a37c-4930-923c-ee9364f88418",
    "memory_type": "short_term",
    "content": "DELETED",
    "metadata": {
      "type": "cache",
      "key": "trailtag:003df7448e5e1d3435634e2bae6d1ca7",
      "deleted": true,
      "deleted_at": 1757085962.847085
    },
    "agent_role": null,
    "task_id": null,
    "video_id": null,
    "created_at": "2025-09-05T15:26:02.847093+00:00",
    "updated_at": "2025-09-05T15:26:02.847094+00:00",
    "expires_at": null
  },
  {
    "id": "319356ea-453e-4b79-a8f2-0dba9441f7b9",
    "memory_type": "short_term",
    "content": "{\"job_id\": \"65130af3-2fc5-48cc-96d3-426c81d5beea\", \"video_id\": \"kp2Prt6jbkc\", \"status\": \"queued\", \"phase\": null, \"progress\": 0.0, \"cached\": false, \"created_at\": \"2025-09-05T15:27:09.483820+00:00\", \"updated_at\": \"2025-09-05T15:27:09.483820+00:00\", \"subtitle_availability\": {\"available\": true, \"manual_subtitles\": [], \"auto_captions\": [\"ar\", \"zh-Hant\", \"nl\", \"fr\", \"de\", \"hi\", \"id\", \"it\", \"ja\", \"ko\", \"pt\", \"ru\", \"es\", \"th\", \"uk\", \"vi\"], \"selected_lang\": null, \"confidence_score\": 0.75}}",
    "metadata": {
      "type": "cache",
      "key": "trailtag:071932d6a06204c070e05d3a33cd38a8",
      "original_query": "job:65130af3-2fc5-48cc-96d3-426c81d5beea",
      "ttl": null,
      "stored_at": 1757086029.483944
    },
    "agent_role": null,
    "task_id": null,
    "video_id": null,
    "created_at": "2025-09-05T15:27:09.483962+00:00",
    "updated_at": "2025-09-05T15:27:09.483962+00:00",
    "expires_at": null
  },
  {
    "id": "b7ae48c6-8836-4645-ae79-4938075a8e5d",
    "memory_type": "short_term",
    "content": "65130af3-2fc5-48cc-96d3-426c81d5beea",
    "metadata": {
      "type": "cache",
      "key": "trailtag:003df7448e5e1d3435634e2bae6d1ca7",
      "original_query": "video_job:kp2Prt6jbkc",
      "ttl": null,
      "stored_at": 1757086029.485151
    },
    "agent_role": null,
    "task_id": null,
    "video_id": null,
    "created_at": "2025-09-05T15:27:09.485190+00:00",
    "updated_at": "2025-09-05T15:27:09.485274+00:00",
    "expires_at": null
  },
  {
    "id": "eb4574f1-a4bd-4f0a-8ed8-6d436fd95f80",
    "memory_type": "short_term",
    "content": "{\"job_id\": \"65130af3-2fc5-48cc-96d3-426c81d5beea\", \"video_id\": \"kp2Prt6jbkc\", \"status\": \"running\", \"phase\": \"metadata\", \"progress\": 0.0, \"cached\": false, \"created_at\": \"2025-09-05T15:27:09.483820+00:00\", \"updated_at\": \"2025-09-05T15:27:09.504175+00:00\", \"subtitle_availability\": {\"available\": true, \"manual_subtitles\": [], \"auto_captions\": [\"ar\", \"zh-Hant\", \"nl\", \"fr\", \"de\", \"hi\", \"id\", \"it\", \"ja\", \"ko\", \"pt\", \"ru\", \"es\", \"th\", \"uk\", \"vi\"], \"selected_lang\": null, \"confidence_score\": 0.75}}",
    "metadata": {
      "type": "cache",
      "key": "trailtag:071932d6a06204c070e05d3a33cd38a8",
      "original_query": "job:65130af3-2fc5-48cc-96d3-426c81d5beea",
      "ttl": null,
      "stored_at": 1757086029.5044842
    },
    "agent_role": null,
    "task_id": null,
    "video_id": null,
    "created_at": "2025-09-05T15:27:09.504519+00:00",
    "updated_at": "2025-09-05T15:27:09.504524+00:00",
    "expires_at": null
  },
  {
    "id": "2c255757-a4bb-404a-a275-ef0621d07250",
    "memory_type": "short_term",
    "content": "{\"job_id\": \"65130af3-2fc5-48cc-96d3-426c81d5beea\", \"video_id\": \"kp2Prt6jbkc\", \"status\": \"running\", \"phase\": \"metadata\", \"progress\": 5, \"cached\": false, \"created_at\": \"2025-09-05T15:27:09.483820+00:00\", \"updated_at\": \"2025-09-05T15:27:09.506408+00:00\", \"subtitle_availability\": {\"available\": true, \"manual_subtitles\": [], \"auto_captions\": [\"ar\", \"zh-Hant\", \"nl\", \"fr\", \"de\", \"hi\", \"id\", \"it\", \"ja\", \"ko\", \"pt\", \"ru\", \"es\", \"th\", \"uk\", \"vi\"], \"selected_lang\": null, \"confidence_score\": 0.75}}",
    "metadata": {
      "type": "cache",
      "key": "trailtag:071932d6a06204c070e05d3a33cd38a8",
      "original_query": "job:65130af3-2fc5-48cc-96d3-426c81d5beea",
      "ttl": null,
      "stored_at": 1757086029.506453
    },
    "agent_role": null,
    "task_id": null,
    "video_id": null,
    "created_at": "2025-09-05T15:27:09.506494+00:00",
    "updated_at": "2025-09-05T15:27:09.506497+00:00",
    "expires_at": null
  },
  {
    "id": "a0f1cef7-7314-4011-875f-a9a43920ed60",
    "memory_type": "short_term",
    "content": "{\"job_id\": \"65130af3-2fc5-48cc-96d3-426c81d5beea\", \"video_id\": \"kp2Prt6jbkc\", \"status\": \"failed\", \"phase\": \"geocode\", \"progress\": 0, \"cached\": false, \"created_at\": \"2025-09-05T15:27:09.483820+00:00\", \"updated_at\": \"2025-09-05T15:27:10.530989+00:00\", \"subtitle_availability\": {\"available\": true, \"manual_subtitles\": [], \"auto_captions\": [\"ar\", \"zh-Hant\", \"nl\", \"fr\", \"de\", \"hi\", \"id\", \"it\", \"ja\", \"ko\", \"pt\", \"ru\", \"es\", \"th\", \"uk\", \"vi\"], \"selected_lang\": null, \"confidence_score\": 0.75}, \"error\": {\"type\": \"exception\", \"message\": \"\\\"Crew\\\" object has no field \\\"kickoff\\\"\"}}",
    "metadata": {
      "type": "cache",
      "key": "trailtag:071932d6a06204c070e05d3a33cd38a8",
      "original_query": "job:65130af3-2fc5-48cc-96d3-426c81d5beea",
      "ttl": null,
      "stored_at": 1757086030.5310369
    },
    "agent_role": null,
    "task_id": null,
    "video_id": null,
    "created_at": "2025-09-05T15:27:10.531050+00:00",
    "updated_at": "2025-09-05T15:27:10.531051+00:00",
    "expires_at": null
  },
  {
    "id": "c8974c1a-5fcf-4efb-b36a-bc01c6383b64",
    "memory_type": "short_term",
    "content": "DELETED",
    "metadata": {
      "type": "cache",
      "key": "trailtag:003df7448e5e1d3435634e2bae6d1ca7",
      "deleted": true,
      "deleted_at": 1757086030.5318131
    },
    "agent_role": null,
    "task_id": null,
    "video_id": null,
    "created_at": "2025-09-05T15:27:10.531820+00:00",
    "updated_at": "2025-09-05T15:27:10.531821+00:00",
    "expires_at": null
  },
  {
    "id": "f58b57e4-df85-48ef-8dca-6566c24dc041",
    "memory_type": "short_term",
    "content": "{\"job_id\": \"f6c1017e-5d2a-4673-80ce-48b1b216497c\", \"video_id\": \"kp2Prt6jbkc\", \"status\": \"queued\", \"phase\": null, \"progress\": 0.0, \"cached\": false, \"created_at\": \"2025-09-05T15:28:15.767830+00:00\", \"updated_at\": \"2025-09-05T15:28:15.767830+00:00\", \"subtitle_availability\": {\"available\": true, \"manual_subtitles\": [], \"auto_captions\": [\"ar\", \"zh-Hant\", \"nl\", \"fr\", \"de\", \"hi\", \"id\", \"it\", \"ja\", \"ko\", \"pt\", \"ru\", \"es\", \"th\", \"uk\", \"vi\"], \"selected_lang\": null, \"confidence_score\": 0.75}}",
    "metadata": {
      "type": "cache",
      "key": "trailtag:47a9d646819f67d5bb7a5fdd13fe8fbe",
      "original_query": "job:f6c1017e-5d2a-4673-80ce-48b1b216497c",
      "ttl": null,
      "stored_at": 1757086095.7679749
    },
    "agent_role": null,
    "task_id": null,
    "video_id": null,
    "created_at": "2025-09-05T15:28:15.768001+00:00",
    "updated_at": "2025-09-05T15:28:15.768003+00:00",
    "expires_at": null
  },
  {
    "id": "b03ef086-9084-4b1a-82d8-852d0561b301",
    "memory_type": "short_term",
    "content": "f6c1017e-5d2a-4673-80ce-48b1b216497c",
    "metadata": {
      "type": "cache",
      "key": "trailtag:003df7448e5e1d3435634e2bae6d1ca7",
      "original_query": "video_job:kp2Prt6jbkc",
      "ttl": null,
      "stored_at": 1757086095.770912
    },
    "agent_role": null,
    "task_id": null,
    "video_id": null,
    "created_at": "2025-09-05T15:28:15.770937+00:00",
    "updated_at": "2025-09-05T15:28:15.770940+00:00",
    "expires_at": null
  },
  {
    "id": "f6845cc2-3870-4b63-ac57-2b045635e935",
    "memory_type": "short_term",
    "content": "{\"job_id\": \"f6c1017e-5d2a-4673-80ce-48b1b216497c\", \"video_id\": \"kp2Prt6jbkc\", \"status\": \"running\", \"phase\": \"metadata\", \"progress\": 0.0, \"cached\": false, \"created_at\": \"2025-09-05T15:28:15.767830+00:00\", \"updated_at\": \"2025-09-05T15:28:15.783312+00:00\", \"subtitle_availability\": {\"available\": true, \"manual_subtitles\": [], \"auto_captions\": [\"ar\", \"zh-Hant\", \"nl\", \"fr\", \"de\", \"hi\", \"id\", \"it\", \"ja\", \"ko\", \"pt\", \"ru\", \"es\", \"th\", \"uk\", \"vi\"], \"selected_lang\": null, \"confidence_score\": 0.75}}",
    "metadata": {
      "type": "cache",
      "key": "trailtag:47a9d646819f67d5bb7a5fdd13fe8fbe",
      "original_query": "job:f6c1017e-5d2a-4673-80ce-48b1b216497c",
      "ttl": null,
      "stored_at": 1757086095.7834182
    },
    "agent_role": null,
    "task_id": null,
    "video_id": null,
    "created_at": "2025-09-05T15:28:15.783449+00:00",
    "updated_at": "2025-09-05T15:28:15.783451+00:00",
    "expires_at": null
  },
  {
    "id": "bbded879-6062-4157-88b3-da2003bf7fba",
    "memory_type": "short_term",
    "content": "{\"job_id\": \"f6c1017e-5d2a-4673-80ce-48b1b216497c\", \"video_id\": \"kp2Prt6jbkc\", \"status\": \"running\", \"phase\": \"metadata\", \"progress\": 5, \"cached\": false, \"created_at\": \"2025-09-05T15:28:15.767830+00:00\", \"updated_at\": \"2025-09-05T15:28:15.785202+00:00\", \"subtitle_availability\": {\"available\": true, \"manual_subtitles\": [], \"auto_captions\": [\"ar\", \"zh-Hant\", \"nl\", \"fr\", \"de\", \"hi\", \"id\", \"it\", \"ja\", \"ko\", \"pt\", \"ru\", \"es\", \"th\", \"uk\", \"vi\"], \"selected_lang\": null, \"confidence_score\": 0.75}}",
    "metadata": {
      "type": "cache",
      "key": "trailtag:47a9d646819f67d5bb7a5fdd13fe8fbe",
      "original_query": "job:f6c1017e-5d2a-4673-80ce-48b1b216497c",
      "ttl": null,
      "stored_at": 1757086095.785271
    },
    "agent_role": null,
    "task_id": null,
    "video_id": null,
    "created_at": "2025-09-05T15:28:15.785290+00:00",
    "updated_at": "2025-09-05T15:28:15.785291+00:00",
    "expires_at": null
  },
  {
    "id": "5c64f39e-9369-4013-844f-b597dbf636aa",
    "memory_type": "short_term",
    "content": "{\"job_id\": \"f6c1017e-5d2a-4673-80ce-48b1b216497c\", \"video_id\": \"kp2Prt6jbkc\", \"status\": \"failed\", \"phase\": \"geocode\", \"progress\": 0, \"cached\": false, \"created_at\": \"2025-09-05T15:28:15.767830+00:00\", \"updated_at\": \"2025-09-05T15:28:16.288542+00:00\", \"subtitle_availability\": {\"available\": true, \"manual_subtitles\": [], \"auto_captions\": [\"ar\", \"zh-Hant\", \"nl\", \"fr\", \"de\", \"hi\", \"id\", \"it\", \"ja\", \"ko\", \"pt\", \"ru\", \"es\", \"th\", \"uk\", \"vi\"], \"selected_lang\": null, \"confidence_score\": 0.75}, \"error\": {\"type\": \"exception\", \"message\": \"\\\"Crew\\\" object has no field \\\"kickoff\\\"\"}}",
    "metadata": {
      "type": "cache",
      "key": "trailtag:47a9d646819f67d5bb7a5fdd13fe8fbe",
      "original_query": "job:f6c1017e-5d2a-4673-80ce-48b1b216497c",
      "ttl": null,
      "stored_at": 1757086096.2885902
    },
    "agent_role": null,
    "task_id": null,
    "video_id": null,
    "created_at": "2025-09-05T15:28:16.288605+00:00",
    "updated_at": "2025-09-05T15:28:16.288606+00:00",
    "expires_at": null
  },
  {
    "id": "4b957c71-a114-4780-a323-acc335915944",
    "memory_type": "short_term",
    "content": "DELETED",
    "metadata": {
      "type": "cache",
      "key": "trailtag:003df7448e5e1d3435634e2bae6d1ca7",
      "deleted": true,
      "deleted_at": 1757086096.289502
    },
    "agent_role": null,
    "task_id": null,
    "video_id": null,
    "created_at": "2025-09-05T15:28:16.289519+00:00",
    "updated_at": "2025-09-05T15:28:16.289521+00:00",
    "expires_at": null
  }
]
